flake8_commas/__init__.py
flake8_commas/_base.py
flake8_commas_x-3.0.0.post2.dist-info/LICENSE
flake8_commas_x-3.0.0.post2.dist-info/METADATA
flake8_commas_x-3.0.0.post2.dist-info/WHEEL
flake8_commas_x-3.0.0.post2.dist-info/entry_points.txt
flake8_commas_x-3.0.0.post2.dist-info/top_level.txt
flake8_commas_x-3.0.0.post2.dist-info/RECORD
