Metadata-Version: 2.1
Name: flake8-commas-x
Version: 3.0.0.post2
Summary: Flake8 lint for trailing commas.
Home-page: https://github.com/PeterJCLaw/flake8-commas/tree/x-main
Author: Peter Law
Author-email: PeterJCLaw@gmail.com
Maintainer: Peter Law
Maintainer-email: PeterJCLaw@gmail.com
Classifier: Environment :: Console
Classifier: Intended Audience :: Developers
Classifier: Operating System :: OS Independent
Classifier: License :: OSI Approved :: MIT License
Classifier: Programming Language :: Python
Classifier: Programming Language :: Python :: 3.8
Classifier: Programming Language :: Python :: 3.9
Classifier: Programming Language :: Python :: 3.10
Classifier: Programming Language :: Python :: 3.11
Classifier: Programming Language :: Python :: 3.12
Classifier: Topic :: Software Development :: Libraries :: Python Modules
Classifier: Topic :: Software Development :: Quality Assurance
Classifier: Framework :: Flake8
Requires-Python: >=3.8
License-File: LICENSE
Requires-Dist: flake8 >=5
